README.md
setup.py
datamunger/__init__.py
datamunger/imputeKNN.py
datamunger.egg-info/PKG-INFO
datamunger.egg-info/SOURCES.txt
datamunger.egg-info/dependency_links.txt
datamunger.egg-info/not-zip-safe
datamunger.egg-info/requires.txt
datamunger.egg-info/top_level.txt