Metadata-Version: 1.0
Name: datamunger
Version: 0.3.9
Summary: Set of tools for Nan and Outlier Imputation
Home-page: https://github.com/bacross/datamunger
Author: bacross
Author-email: pydatamunger@gmail.com
License: MIT
Platform: UNKNOWN
